qwen7b_tr/__init__.py
qwen7b_tr/__main__.py
qwen7b_tr/__main__.py-
qwen7b_tr-0.1.0a4.dist-info/entry_points.txt
qwen7b_tr-0.1.0a4.dist-info/LICENSE
qwen7b_tr-0.1.0a4.dist-info/METADATA
qwen7b_tr-0.1.0a4.dist-info/WHEEL
qwen7b_tr-0.1.0a4.dist-info/RECORD
